README.md
setup.py
gsexamples/__init__.py
gsexamples/tjarnberg2013.py
scikit_grni.egg-info/PKG-INFO
scikit_grni.egg-info/SOURCES.txt
scikit_grni.egg-info/dependency_links.txt
scikit_grni.egg-info/not-zip-safe
scikit_grni.egg-info/requires.txt
scikit_grni.egg-info/top_level.txt
skgrni/__init__.py
skgrni/data.py
skgrni/inference.py
skgrni/junk_func.py
skgrni/load.py
skgrni/metrics.py
skgrni/properties.py
skgrni/stats.py
skgrni/utils.py
skgrni/visualization.py