Metadata-Version: 1.2
Name: scikit-grni
Version: 0.1.3
Summary: A set of modules for simplifying gene regulatory network inference, a branch of machine learning focused towards the problem of uncovering biological function from biological measurements.
Home-page: https://gitlab.com/Xparx/scikit-grni
Author: Andreas Tjärnberg
Author-email: andreas.tjarnberg@fripost.org
License: LGPL
Platform: UNKNOWN
Requires-Python: >=3
